[
    {
        "id" : 1,
        "name" : "Sample 1",
        "description" : "Sample description"
    },
    {
        "id" : 2,
        "name" : "Sample 2",
        "description" : "Sample description"
    },
    {
        "id" : 3,
        "name" : "Sample 3",
        "description" : "Sample description"
    },
    {
        "id" : 4,
        "name" : "Sample 4",
        "description" : "Sample description"
    },
    {
        "id" : 5,
        "name" : "Sample 5",
        "description" : "Sample description"
    }
]